{
  "5200menu": {
    "description": "5200 Menu (Prototype)",
    "publisher": "Atari",
    "year": "1983"
  },
  "5200temp": {
    "description": "5200 Tempest",
    "publisher": "Atariage",
    "year": "2012"
  },
  "achase": {
    "description": "Astro Chase",
    "publisher": "Parker Brothers",
    "year": "1984"
  },
  "aep": {
    "description": "A.E. (Prototype)",
    "publisher": "Brøderbund Software Inc",
    "year": "1982"
  },
  "asteroid": {
    "description": "Asteroids (Prototype)",
    "publisher": "Atari",
    "year": "1982"
  },
  "ballblaz": {
    "description": "Ballblazer",
    "publisher": "Atari / Lucasfilm",
    "year": "1986"
  },
  "barbball": {
    "description": "Barroom Baseball (Prototype)",
    "publisher": "Atari",
    "year": "1983"
  },
  "bbsb": {
    "description": "Bounty Bob Strikes Back!",
    "publisher": "Big Five Software",
    "year": "1984"
  },
  "beamridr": {
    "description": "Beamrider",
    "publisher": "Activision",
    "year": "1983"
  },
  "berzerk": {
    "description": "Berzerk",
    "publisher": "Atari",
    "year": "1983"
  },
  "blaster": {
    "description": "Blaster (Prototype)",
    "publisher": "Atari",
    "year": "1984"
  },
  "blckbelt": {
    "description": "Black Belt (Prototype)",
    "publisher": "Atari",
    "year": "1983"
  },
  "blueprnt": {
    "description": "Blue-Print",
    "publisher": "CBS Electronics / Bally Midway MFG. Co.",
    "year": "1982"
  },
  "boogie": {
    "description": "Boogie (Demo)",
    "publisher": "Atari",
    "year": "1982"
  },
  "buckrog": {
    "description": "Buck Rogers - Planet of Zoom",
    "publisher": "Sega",
    "year": "1983"
  },
  "bzone": {
    "description": "Battlezone (Prototype)",
    "publisher": "Atari",
    "year": "1983"
  },
  "cblast": {
    "description": "Castle Blast",
    "publisher": "<unlicensed>",
    "year": "2002"
  },
  "ccrisis": {
    "description": "Castle Crisis",
    "publisher": "<unlicensed>",
    "year": "2004"
  },
  "centiped": {
    "description": "Centipede",
    "publisher": "Atari",
    "year": "1982"
  },
  "choplift": {
    "description": "Choplifter!",
    "publisher": "Atari",
    "year": "1984"
  },
  "cntrmsre": {
    "description": "Countermeasure",
    "publisher": "Atari",
    "year": "1982"
  },
  "congo": {
    "description": "Congo Bongo",
    "publisher": "Sega",
    "year": "1983"
  },
  "decathln": {
    "description": "The Activision Decathlon",
    "publisher": "Activision",
    "year": "1983"
  },
  "defender": {
    "description": "Defender",
    "publisher": "Atari",
    "year": "1982"
  },
  "dfactor": {
    "description": "The Dreadnaught Factor",
    "publisher": "Activision",
    "year": "1983"
  },
  "digdug": {
    "description": "Dig Dug",
    "publisher": "Atari",
    "year": "1983"
  },
  "docastle": {
    "description": "Mr. Do!'s Castle",
    "publisher": "Parker Brothers",
    "year": "1984"
  },
  "finaltst": {
    "description": "Atari PAM Final System Test (Rev 1.0)",
    "publisher": "Atari",
    "year": "1982"
  },
  "flegacy": {
    "description": "Final Legacy (Prototype)",
    "publisher": "Atari",
    "year": "1984"
  },
  "fractal": {
    "description": "Rescue on Fractalus!",
    "publisher": "Atari / Lucasfilm",
    "year": "1986"
  },
  "friskyt": {
    "description": "Frisky Tom (Prototype)",
    "publisher": "Atari",
    "year": "1983"
  },
  "frogger": {
    "description": "Frogger",
    "publisher": "Parker Brothers",
    "year": "1983"
  },
  "frogger2": {
    "description": "Frogger II: Threeedeep!",
    "publisher": "Parker Brothers",
    "year": "1983"
  },
  "galaxian": {
    "description": "Galaxian",
    "publisher": "Atari",
    "year": "1982"
  },
  "gorf": {
    "description": "Gorf",
    "publisher": "CBS Electronics / Bally Midway MFG. Co.",
    "year": "1982"
  },
  "gremlins": {
    "description": "Gremlins",
    "publisher": "Atari",
    "year": "1984"
  },
  "gyruss": {
    "description": "Gyruss",
    "publisher": "Parker Brothers",
    "year": "1984"
  },
  "hero": {
    "description": "H.E.R.O.",
    "publisher": "Activision",
    "year": "1984"
  },
  "jbond": {
    "description": "James Bond",
    "publisher": "Parker Brothers",
    "year": "1984"
  },
  "jedidsb": {
    "description": "Star Wars - Return of the Jedi - Death Star Battle",
    "publisher": "Parker Brothers",
    "year": "1983"
  },
  "joust": {
    "description": "Joust",
    "publisher": "Atari",
    "year": "1983"
  },
  "jrpacman": {
    "description": "Jr Pacman (Prototype)",
    "publisher": "Atari",
    "year": "1984"
  },
  "jungleh": {
    "description": "Jungle Hunt",
    "publisher": "Atari",
    "year": "1983"
  },
  "kaboom": {
    "description": "Kaboom!",
    "publisher": "Activision",
    "year": "1983"
  },
  "kangaroo": {
    "description": "Kangaroo",
    "publisher": "Atari",
    "year": "1982"
  },
  "keykaper": {
    "description": "Keystone Kapers",
    "publisher": "Activision",
    "year": "1983"
  },
  "koffiyk": {
    "description": "Koffi: Yellow Kopter",
    "publisher": "<unlicensed>",
    "year": "2002"
  },
  "kshoot": {
    "description": "K-Razy Shoot Out",
    "publisher": "CBS Electronics / Kay Enterprizes Co.",
    "year": "1982"
  },
  "laststar": {
    "description": "The Last Starfighter (Prototype)",
    "publisher": "Atari",
    "year": "1984"
  },
  "looneyh": {
    "description": "Looney Tunes Hotel (Prototype)",
    "publisher": "Atari",
    "year": "1983"
  },
  "mario": {
    "description": "Mario Bros.",
    "publisher": "Atari",
    "year": "1983"
  },
  "meebzork": {
    "description": "Meebzork (Prototype)",
    "publisher": "Atari",
    "year": "1983"
  },
  "megmania": {
    "description": "MegaMania",
    "publisher": "Activision",
    "year": "1984"
  },
  "meteorit": {
    "description": "Meteorites",
    "publisher": "Electra Concepts",
    "year": "1983"
  },
  "microgam": {
    "description": "Microgammon SB (Prototype)",
    "publisher": "Atari",
    "year": "1983"
  },
  "milliped": {
    "description": "Millipede (Prototype)",
    "publisher": "Atari",
    "year": "1984"
  },
  "mine2049": {
    "description": "Miner 2049er",
    "publisher": "Big Five Software",
    "year": "1983"
  },
  "minigolf": {
    "description": "Miniature Golf (Prototype)",
    "publisher": "Atari",
    "year": "1983"
  },
  "missile": {
    "description": "Missile Command",
    "publisher": "Atari",
    "year": "1982"
  },
  "mking": {
    "description": "Mountain King",
    "publisher": "CBS Electronics",
    "year": "1983"
  },
  "montezum": {
    "description": "Montezuma's Revenge",
    "publisher": "Parker Brothers",
    "year": "1984"
  },
  "mpatrol": {
    "description": "Moon Patrol",
    "publisher": "Atari",
    "year": "1983"
  },
  "mspacman": {
    "description": "Ms. Pac-Man",
    "publisher": "Atari",
    "year": "1983"
  },
  "pacman": {
    "description": "Pac-Man",
    "publisher": "Atari",
    "year": "1982"
  },
  "pamdg23": {
    "description": "Atari PAM Diagnostics (Rev 2.3)",
    "publisher": "Atari",
    "year": "1983"
  },
  "pamdiag2": {
    "description": "PAM Diag 2.0",
    "publisher": "Atari",
    "year": "1982"
  },
  "pengo": {
    "description": "Pengo",
    "publisher": "Atari",
    "year": "1983"
  },
  "petetest": {
    "description": "PAM: Pete's Test (USA)",
    "publisher": "Atari",
    "year": "1982"
  },
  "pitfall": {
    "description": "Pitfall!",
    "publisher": "Activision",
    "year": "1984"
  },
  "pitfall2": {
    "description": "David Crane's Pitfall II - Lost Caverns",
    "publisher": "Activision",
    "year": "1983"
  },
  "polepos": {
    "description": "Pole Position",
    "publisher": "Atari",
    "year": "1983"
  },
  "popeye": {
    "description": "Popeye",
    "publisher": "Parker Brothers",
    "year": "1983"
  },
  "qbert": {
    "description": "Q*bert",
    "publisher": "Parker Brothers",
    "year": "1983"
  },
  "qix": {
    "description": "Qix",
    "publisher": "Atari",
    "year": "1982"
  },
  "quintana": {
    "description": "Quest for Quintana Roo",
    "publisher": "Sunrise",
    "year": "1984"
  },
  "riveraid": {
    "description": "River Raid",
    "publisher": "Activision",
    "year": "1983"
  },
  "roadrun": {
    "description": "Road Runner (Prototype)",
    "publisher": "Atari",
    "year": "1982"
  },
  "robotron": {
    "description": "Robotron: 2084",
    "publisher": "Atari",
    "year": "1983"
  },
  "rsbaseb": {
    "description": "RealSports Baseball",
    "publisher": "Atari",
    "year": "1983"
  },
  "rsbasket": {
    "description": "RealSports Basketball (19831216)",
    "publisher": "Atari",
    "year": "1983"
  },
  "rsbasket1": {
    "description": "RealSports Basketball (Prototype, 19831031)",
    "publisher": "Atari",
    "year": "1983"
  },
  "rsbasket2": {
    "description": "RealSports Basketball (Prototype, 19821105)",
    "publisher": "Atari",
    "year": "1982"
  },
  "rsfootb": {
    "description": "RealSports Football",
    "publisher": "Atari",
    "year": "1982"
  },
  "rssoccer": {
    "description": "RealSports Soccer",
    "publisher": "Atari",
    "year": "1982"
  },
  "rstennis": {
    "description": "RealSports Tennis",
    "publisher": "Atari",
    "year": "1982"
  },
  "sbrkout": {
    "description": "Super Breakout",
    "publisher": "Atari",
    "year": "1982"
  },
  "scobra": {
    "description": "Super Cobra",
    "publisher": "Parker Brothers",
    "year": "1983"
  },
  "shuttle": {
    "description": "Space Shuttle - A Journey Into Space",
    "publisher": "Activision",
    "year": "1983"
  },
  "spaceinv": {
    "description": "Space Invaders",
    "publisher": "Atari",
    "year": "1982"
  },
  "spacman": {
    "description": "Super Pac-Man (Prototype)",
    "publisher": "Atari",
    "year": "1984"
  },
  "spcedngn": {
    "description": "Space Dungeon",
    "publisher": "Atari",
    "year": "1983"
  },
  "spitfire": {
    "description": "Spitfire (Prototype)",
    "publisher": "Atari",
    "year": "1983"
  },
  "sprtgoof": {
    "description": "Sport Goofy (Prototype)",
    "publisher": "Atari",
    "year": "1983"
  },
  "stargate": {
    "description": "Stargate (Prototype)",
    "publisher": "Atari",
    "year": "1984"
  },
  "starraid": {
    "description": "Star Raiders",
    "publisher": "Atari",
    "year": "1982"
  },
  "startrek": {
    "description": "Star Trek",
    "publisher": "Sega",
    "year": "1982"
  },
  "starwars": {
    "description": "Star Wars - The Arcade Game",
    "publisher": "Parker Brothers",
    "year": "1983"
  },
  "tempest": {
    "description": "Tempest (Prototype)",
    "publisher": "Atari",
    "year": "1983"
  },
  "trackfld": {
    "description": "Track and Field (Prototype)",
    "publisher": "Atari",
    "year": "1984"
  },
  "vanguard": {
    "description": "Vanguard",
    "publisher": "Atari",
    "year": "1983"
  },
  "wow": {
    "description": "Wizard of Wor",
    "publisher": "CBS Electronics",
    "year": "1983"
  },
  "xari": {
    "description": "Xari Arena (Prototype)",
    "publisher": "Atari",
    "year": "1983"
  },
  "xevious": {
    "description": "Xevious (Prototype)",
    "publisher": "Atari",
    "year": "1984"
  },
  "yllowsub": {
    "description": "Yellow Sub Demo",
    "publisher": "Atari",
    "year": "1983"
  },
  "zaxxon": {
    "description": "Zaxxon",
    "publisher": "Sega",
    "year": "1984"
  },
  "zenji": {
    "description": "Zenji",
    "publisher": "Activision",
    "year": "1984"
  },
  "zonerngr": {
    "description": "Zone Ranger",
    "publisher": "Activision",
    "year": "1984"
  }
}